{
    "$schema": "https://schema.management.azure.com/schemas/2015-01-01/deploymentParameters.json#",
    "contentVersion": "1.0.0.0",
    "parameters": {
        "location": {
            "value": "eastus"
        },
        "networkInterfaceName": {
            "value": "dc-0161"
        },
        "networkSecurityGroupName": {
            "value": "DC-01-nsg"
        },
        "networkSecurityGroupRules": {
            "value": [
                {
                    "name": "RDP",
                    "properties": {
                        "priority": 300,
                        "protocol": "TCP",
                        "access": "Allow",
                        "direction": "Inbound",
                        "sourceAddressPrefix": "*",
                        "sourcePortRange": "*",
                        "destinationAddressPrefix": "*",
                        "destinationPortRange": "3389"
                    }
                }
            ]
        },
        "subnetName": {
            "value": "default"
        },
        "virtualNetworkName": {
            "value": "myklix-net"
        },
        "addressPrefixes": {
            "value": [
                "10.0.0.0/24"
            ]
        },
        "subnets": {
            "value": [
                {
                    "name": "default",
                    "properties": {
                        "addressPrefix": "10.0.0.0/24"
                    }
                }
            ]
        },
        "publicIpAddressName": {
            "value": "DC-01-ip"
        },
        "publicIpAddressType": {
            "value": "Dynamic"
        },
        "publicIpAddressSku": {
            "value": "Basic"
        },
        "virtualMachineName": {
            "value": "DC-01"
        },
        "virtualMachineComputerName": {
            "value": "DC-01"
        },
        "virtualMachineRG": {
            "value": "DC-01_group"
        },
        "osDiskType": {
            "value": "StandardSSD_LRS"
        },
        "virtualMachineSize": {
            "value": "Standard_DS1_v2"
        },
        "adminUsername": {
            "value": "mrklix"
        },
        "adminPassword": {
            "value": null
        },
        "patchMode": {
            "value": "AutomaticByOS"
        }
    }
}